django_model_signals/__init__.py
django_model_signals/apps.py
django_model_signals/dispatcher.py
django_model_signals/manager.py
django_model_signals/models.py
django_model_signals/signals.py
django_model_signals-0.4.3.dist-info/METADATA
django_model_signals-0.4.3.dist-info/WHEEL
django_model_signals-0.4.3.dist-info/licenses/LICENSE.md
django_model_signals-0.4.3.dist-info/RECORD
