Metadata-Version: 2.1
Name: django-model-signals
Version: 0.4.3
Summary: Django Model Signals makes it easier to keep model related business logic in your Django models by allowing them to become transceivers of their own signals, including bulk signals.
Author-email: Digital Valley <techteam@digitalvalley.nl>
License-File: LICENSE.md
Classifier: Development Status :: 3 - Alpha
Classifier: Framework :: Django
Classifier: License :: OSI Approved :: MIT License
Classifier: Programming Language :: Python :: 3
Requires-Python: >=3.7
Requires-Dist: django
